face_group/__init__.py
face_group/api.py
face_group/cli.py
face_group/utils.py
face_group-0.1.11.dist-info/entry_points.txt
face_group-0.1.11.dist-info/WHEEL
face_group-0.1.11.dist-info/METADATA
face_group-0.1.11.dist-info/RECORD
