Metadata-Version: 2.1
Name: face-group
Version: 0.1.11
Summary: Grouping rgb and infra people`s faces by folders using face features.
Home-page: https://github.com/Irlirion/face-group
License: MIT
Author: irlirion
Author-email: irlirion@protonmail.com
Requires-Python: >=3.7,<4.0
Classifier: License :: OSI Approved :: MIT License
Classifier: Programming Language :: Python :: 3
Classifier: Programming Language :: Python :: 3.7
Classifier: Programming Language :: Python :: 3.8
Classifier: Programming Language :: Python :: 3.9
Requires-Dist: face-recognition (>=1.3.0,<2.0.0)
Requires-Dist: rich (>=9.11.1,<10.0.0)
